{
  "type": "Major",
  "name": "Psychology",
  "code": "PSY",
  "degree": "AB",
  "year": 2018,
  "urls": [
    "https://ua.princeton.edu/academic-units/department-psychology",
    "https://psych.princeton.edu/undergraduate-program"
  ],
  "contacts": [
    {
      "type": "Chair",
      "name": "Kenneth A. Norman",
      "email": "knorman@princeton.edu"
    },
    {
      "type": "Associate Chair",
      "name": "Tania Lombrozo",
      "email": "lombrozo@princeton.edu"
    },
    {
      "type": "Director of Undergraduate Studies",
      "name": "Michael S. Graziano",
      "email": "graziano@princeton.edu"
    }
  ],
  "req_list": [
    {
      "name": "Prerequisites",
      "max_counted": 1,
      "min_needed": "ALL",
      "explanation": "The prerequisites for entering the Department of Psychology are successful graded completion of PSY 251 (Quantitative Methods) or a pre-approved statistics course in another department (for example, ORF 245 or ECO 202), along with two other courses from the following list: PSY 101 (Introduction to Psychology), PSY 252 (Social Psychology), PSY 254 (Developmental Psychology), PSY 255 (Cognitive Psychology), or either PSY 258 (Fundamentals of Neuroscience) or NEU 200 (Functional Neuroanatomy). All requests for an alternative set of prerequisites must be approved by the Departmental Representative.",
      "req_list": [
        {
          "name": "Quantitative Methods",
          "max_counted": 1,
          "min_needed": 1,
          "explanation": "The prerequisites for entering the Department of Psychology are successful graded completion of PSY 251 (Quantitative Methods) or a pre-approved statistics course in another department (for example, ORF 245 or ECO 202).",
          "course_list": [
            "PSY 251",
            "ORF 245",
            "ECO 202"
          ]
        },
        {
          "name": "Introductory Courses",
          "max_counted": 1,
          "min_needed": 1,
          "explanation": "PSY 101 (Introduction to Psychology), PSY 252 (Social Psychology), PSY 254 (Developmental Psychology), PSY 255 (Cognitive Psychology), or either PSY 258 (Fundamentals of Neuroscience) or NEU 200 (Functional Neuroanatomy).",
          "double_counting_allowed": true,
          "req_list": [
            {
              "name": null,
              "max_counted": null,
              "min_needed": null,
              "explanation": null,
              "course_list": [
                "PSY 101",
                "PSY 252",
                "PSY 254",
                "PSY 255"
              ]
            },
            {
              "name": null,
              "max_counted": 1,
              "min_needed": null,
              "explanation": null,
              "course_list": [
                "PSY 258",
                "NEU 200"
              ]
            }
          ]
        }
      ]
    },
    {
      "name": "Departmental Courses",
      "max_counted": 1,
      "min_needed": 8,
      "explanation": "The psychology concentration requires graded completion (without PDF) of at least eight courses within the department in addition to the three prerequisite courses. If they were not already taken as prerequisites, students must take PSY 252, PSY 255, and either PSY 258 or NEU 200. It is recommended that students finish these three courses by the end of junior year. One of the eight departmental courses must be PSY 300 (Research Methods in Psychology), which must be completed by the end of junior year. Of the remaining departmental courses, all must be 200-level or higher and at least four must be 300-level or higher. Students can take up to two cognate courses from other departments, approved by the Psychology Departmental Representative, to count as departmental courses.",
      "req_list": [
        {
          "name": "Required Departmentals",
          "max_counted": 4,
          "min_needed": 4,
          "explanation": "If they were not already taken as prerequisites, students must take PSY 252, PSY 255, and either PSY 258 or NEU 200. It is recommended that students finish these three courses by the end of junior year. One of the eight departmental courses must be PSY 300 (Research Methods in Psychology), which must be completed by the end of junior year.",
          "completed_by_semester": 6,
          "req_list": [
            {
              "name": null,
              "max_counted": null,
              "min_needed": null,
              "explanation": null,
              "course_list": [
                "PSY 252",
                "PSY 255",
                "PSY 300"
              ]
            },
            {
              "name": null,
              "max_counted": 1,
              "min_needed": 1,
              "explanation": null,
              "course_list": [
                "PSY 258",
                "NEU 200"
              ]
            }
          ]
        },
        {
          "name": "Other Departmentals",
          "max_counted": 4,
          "min_needed": 4,
          "explanation": "Of the remaining departmental courses, all must be 200-level or higher and at least four must be 300-level or higher. Students can take up to two cognate courses from other departments, approved by the Psychology Departmental Representative, to count as departmental courses.",
          "course_list": [
            "PSY 3*",
            "PSY 4*",
            "PSY 5*"
          ]
        }
      ]
    },
    {
      "name": "Independent Work",
      "max_counted": null,
      "min_needed": null,
      "explanation": "<i>Editor's Note: Concentrators of this major do not enroll in any numbered course for this requirement, so TigerPath does not check it.</i>\n\nThe goal of the junior paper (JP) is to acquaint students with focused study in the field of Psychology; develop proficiency in reading and analyzing the professional literature; develop an independent project as preparation for a thesis, and work in close consultation with a faculty member.\n\nStudents write two JP papers, one in the fall semester and one in the spring. For each JP, the student must also give a presentation midway through the semester showing their progress.",
      "no_req": null
    },
    {
      "name": "Senior Thesis",
      "max_counted": null,
      "min_needed": null,
      "explanation": "<i>Editor's Note: Concentrators of this major do not enroll in any numbered course for this requirement, so TigerPath does not check it.</i>\n\nEach psychology senior works in close consultation with a faculty advisor to develop, carry out and write a senior thesis.\n\nStudents can conduct an experimental thesis, a computational thesis, or a theoretical thesis. An experimental thesis should include a comprehensive literature review, findings from at least one original research study (an experiment or a field study) with appropriate statistical analyses, and a general discussion of the findings. A computational thesis should include a review of the literature and description and discussion of the computational models that the student has completed. A theoretical thesis should include a comprehensive review of the research literature on a psychology topic of importance, including an extensive evaluation of the findings and original interpretations, theoretical proposals, or a proposed program of research to add further scientific knowledge.",
      "no_req": null
    }
  ]
}
